{"text": "『勇者と姫巫女の詩』\n\n#zelda #totk #ティアキン2周年 https://t.co/zeQ7rLYW25", "username": "antsubu_0", "tweet_url": "https://twitter.com/antsubu_0/status/1921763053080584629", "first_link": "https://x.com/antsubu_0/status/1921763053080584629/photo/1", "created_at": "May 12, 2025 at 03:03AM", "embed_code": "<blockquote class=\"twitter-tweet\">\n  <p lang=\"en\" dir=\"ltr\">『勇者と姫巫女の詩』\n\n#zelda #totk #ティアキン2周年 https://t.co/zeQ7rLYW25</p>\n  &mdash; つぶあん (@antsubu_0)\n  <a href=\"https://twitter.com/antsubu_0/status/1921763053080584629\">May 12, 2025</a>\n</blockquote>\n<script async src=\"https://platform.twitter.com/widgets.js\" charset=\"utf-8\"></script>\n", "liked_at": "2025-05-12T15:21:50.996730", "source": "ifttt"}