{"text": "北京 https://t.co/J94IIG4tj3", "username": "Beijingshizuo", "tweet_url": "https://twitter.com/Beijingshizuo/status/1867087483412025768", "first_link": "https://x.com/Beijingshizuo/status/1867087483412025768/photo/1", "created_at": "December 12, 2024 at 06:01AM", "embed_code": "<blockquote class=\"twitter-tweet\">\n  <p lang=\"en\" dir=\"ltr\">北京 https://t.co/J94IIG4tj3</p>\n  &mdash; 北京静男 (@Beijingshizuo)\n  <a href=\"https://twitter.com/Beijingshizuo/status/1867087483412025768\">Dec 12, 2024</a>\n</blockquote>\n<script async src=\"https://platform.twitter.com/widgets.js\" charset=\"utf-8\"></script>\n", "liked_at": "2024-12-12T12:17:03.987629", "source": "ifttt"}