{"text": "https://t.co/K8fWGEtwIg", "username": "ducker_tech", "tweet_url": "https://twitter.com/ducker_tech/status/1872489671655305561", "first_link": "https://sizu.me/kamotomoki/posts/c4b67r5cm450", "created_at": "December 27, 2024 at 03:48AM", "embed_code": "<blockquote class=\"twitter-tweet\">\n  <p lang=\"en\" dir=\"ltr\">https://t.co/K8fWGEtwIg</p>\n  &mdash; Kamo Tomoki | 個人開発 (@ducker_tech)\n  <a href=\"https://twitter.com/ducker_tech/status/1872489671655305561\">Dec 27, 2024</a>\n</blockquote>\n<script async src=\"https://platform.twitter.com/widgets.js\" charset=\"utf-8\"></script>\n", "liked_at": "2024-12-28T08:11:26.181478", "source": "ifttt"}