{"text": "Raymarching \nhttps://t.co/2wgeToNKhQ\n\n#glsl #math #threejs #threejsJourney https://t.co/qm8qw3rz4I", "username": "DrinLajci", "tweet_url": "https://twitter.com/DrinLajci/status/1871249069814808786", "first_link": "https://raymarch.vercel.app/", "created_at": "December 23, 2024 at 05:38PM", "embed_code": "<blockquote class=\"twitter-tweet\">\n  <p lang=\"en\" dir=\"ltr\">Raymarching \nhttps://t.co/2wgeToNKhQ\n\n#glsl #math #threejs #threejsJourney https://t.co/qm8qw3rz4I</p>\n  &mdash; Drin Lajci (@DrinLajci)\n  <a href=\"https://twitter.com/DrinLajci/status/1871249069814808786\">Dec 23, 2024</a>\n</blockquote>\n<script async src=\"https://platform.twitter.com/widgets.js\" charset=\"utf-8\"></script>\n", "liked_at": "2024-12-24T11:56:14.165796", "source": "ifttt"}