{"text": "とても良かった。バックアップの基礎が一通り書いていた。Web上にある断片情報を集めればおおよそ同じ知識は得られるかもしれないが、コンパクトに一箇所にまとまっている価値は大きい。バックアップの知識は多かれ少なかれ誰もが必要なので読んでおいて損はないと思う\nhttps://t.co/mwqJQfLrMy", "username": "satoru_takeuchi", "tweet_url": "https://twitter.com/satoru_takeuchi/status/1895799039066849332", "first_link": "https://amzn.to/3F3oHZO", "created_at": "March 01, 2025 at 11:31AM", "embed_code": "<blockquote class=\"twitter-tweet\">\n  <p lang=\"en\" dir=\"ltr\">とても良かった。バックアップの基礎が一通り書いていた。Web上にある断片情報を集めればおおよそ同じ知識は得られるかもしれないが、コンパクトに一箇所にまとまっている価値は大きい。バックアップの知識は多かれ少なかれ誰もが必要なので読んでおいて損はないと思う\nhttps://t.co/mwqJQfLrMy</p>\n  &mdash; sat (@satoru_takeuchi)\n  <a href=\"https://twitter.com/satoru_takeuchi/status/1895799039066849332\">Mar 1, 2025</a>\n</blockquote>\n<script async src=\"https://platform.twitter.com/widgets.js\" charset=\"utf-8\"></script>\n", "liked_at": "2025-03-01T13:07:05.189922", "source": "ifttt"}