{"text": "would you break it free?👀 https://t.co/zrigdVT7Hq https://t.co/H5mJPRllHD", "username": "womp3D", "tweet_url": "https://twitter.com/womp3D/status/1902747243444052183", "first_link": "https://x.com/womp3D/status/1902747243444052183/video/1", "created_at": "March 20, 2025 at 03:41PM", "embed_code": "<blockquote class=\"twitter-tweet\">\n  <p lang=\"en\" dir=\"ltr\">would you break it free?👀 https://t.co/zrigdVT7Hq https://t.co/H5mJPRllHD</p>\n  &mdash; Womp (@womp3D)\n  <a href=\"https://twitter.com/womp3D/status/1902747243444052183\">Mar 20, 2025</a>\n</blockquote>\n<script async src=\"https://platform.twitter.com/widgets.js\" charset=\"utf-8\"></script>\n", "liked_at": "2025-03-20T23:36:14.503187", "source": "ifttt"}