{"text": "Posted to Hatena Blog\nèª­ã‚“ã æœ¬2021ã€œ2024 - ãƒãƒ«ã‚·ãƒ†ã‚¤ã‚¢ https://t.co/kyOkti5TxC\n#ã¯ã¦ãªãƒ–ãƒ­ã‚°", "username": "amagitakayosi", "tweet_url": "https://twitter.com/amagitakayosi/status/1884004345378922591", "first_link": "https://blog.amagi.dev/entry/books-2021-to-2024", "created_at": "January 27, 2025 at 10:23PM", "embed_code": "<blockquote class=\"twitter-tweet\">\n  <p lang=\"en\" dir=\"ltr\">Posted to Hatena Blog\nèª­ã‚“ã æœ¬2021ã€œ2024 - ãƒãƒ«ã‚·ãƒ†ã‚¤ã‚¢ https://t.co/kyOkti5TxC\n#ã¯ã¦ãªãƒ–ãƒ­ã‚°</p>\n  &mdash; ğ˜¼ğ™ˆğ˜¼ğ™‚ğ™„ (@amagitakayosi)\n  <a href=\"https://twitter.com/amagitakayosi/status/1884004345378922591\">Jan 27, 2025</a>\n</blockquote>\n<script async src=\"https://platform.twitter.com/widgets.js\" charset=\"utf-8\"></script>\n", "liked_at": "2025-03-30T14:01:51.675409", "source": "ifttt"}