{"text": "朝から開発部でこれ見て、どうやったらこの課題に遭遇するんだ！？！？などと話したりした（発表めちゃおもろかった〜わかりやすい〜）\n\nPHP Conference Japan 2024: 見えないメモリを観測する  PHP 8 4 `pg result memory size`... https://t.co/u2Rytwflj6 @YouTubeより", "username": "asumikam", "tweet_url": "https://twitter.com/asumikam/status/1909773802369892710", "first_link": "https://youtu.be/HWLFyhd1vEg?si=-4t-LMOmC37f4v2q", "created_at": "April 09, 2025 at 01:02AM", "embed_code": "<blockquote class=\"twitter-tweet\">\n  <p lang=\"en\" dir=\"ltr\">朝から開発部でこれ見て、どうやったらこの課題に遭遇するんだ！？！？などと話したりした（発表めちゃおもろかった〜わかりやすい〜）\n\nPHP Conference Japan 2024: 見えないメモリを観測する  PHP 8 4 `pg result memory size`... https://t.co/u2Rytwflj6 @YouTubeより</p>\n  &mdash; あすみ (@asumikam)\n  <a href=\"https://twitter.com/asumikam/status/1909773802369892710\">Apr 9, 2025</a>\n</blockquote>\n<script async src=\"https://platform.twitter.com/widgets.js\" charset=\"utf-8\"></script>\n", "liked_at": "2025-04-09T11:03:29.172200", "source": "ifttt"}