{
  "activities": [
    {
      "date": "2025-08-07",
      "count": 4,
      "dayName": "木"
    },
    {
      "date": "2025-08-08",
      "count": 8,
      "dayName": "金"
    },
    {
      "date": "2025-08-09",
      "count": 8,
      "dayName": "土"
    },
    {
      "date": "2025-08-10",
      "count": 7,
      "dayName": "日"
    },
    {
      "date": "2025-08-11",
      "count": 6,
      "dayName": "月"
    },
    {
      "date": "2025-08-12",
      "count": 4,
      "dayName": "火"
    },
    {
      "date": "2025-08-13",
      "count": 8,
      "dayName": "水"
    }
  ],
  "lastUpdated": "2025-08-14T05:01:12+09:00"
}