{"tweet_id": "1959203208221630590", "text": "デスJavaScript は \"use death\"; から開始する", "username": "f_subal", "tweet_url": "https://twitter.com/f_subal/status/1959203208221630590", "first_link": "", "created_at": "August 23, 2025 at 10:36AM", "embed_code": "<blockquote class=\"twitter-tweet\">\n  <p lang=\"en\" dir=\"ltr\">デスJavaScript は \"use death\"; から開始する</p>\n  &mdash; 藤秋すばる@K03aコミティア153 (@f_subal)\n  <a href=\"https://twitter.com/f_subal/status/1959203208221630590\">Aug 23, 2025</a>\n</blockquote>\n<script async src=\"https://platform.twitter.com/widgets.js\" charset=\"utf-8\"></script>\n", "liked_at": "2025-08-23T15:36:22.167548", "source": "ifttt"}