{"tweet_id": "1959953030046203936", "text": "技術者として何かを極めるために、何を捨てて、その分を注ぎ込むか。\nそういう意味で映画「国宝」は、めっちゃ心に重く響いた。\n自分も結構、仕事以外のものを「捨てて」、その分を注ぎ込んできたな…\nIT技術者にお勧め！でも、どの劇場も混雑気味なので、鑑賞はお早めに。\nhttps://t.co/F5pQ6VdGRr", "username": "takehora", "tweet_url": "https://twitter.com/takehora/status/1959953030046203936", "first_link": "https://kokuhou-movie.com/", "created_at": "August 25, 2025 at 12:16PM", "embed_code": "<blockquote class=\"twitter-tweet\">\n  <p lang=\"en\" dir=\"ltr\">技術者として何かを極めるために、何を捨てて、その分を注ぎ込むか。\nそういう意味で映画「国宝」は、めっちゃ心に重く響いた。\n自分も結構、仕事以外のものを「捨てて」、その分を注ぎ込んできたな…\nIT技術者にお勧め！でも、どの劇場も混雑気味なので、鑑賞はお早めに。\nhttps://t.co/F5pQ6VdGRr</p>\n  &mdash; Yoichiro Takehora (竹洞 陽一郎) | 株式会社Spelldata (@takehora)\n  <a href=\"https://twitter.com/takehora/status/1959953030046203936\">Aug 25, 2025</a>\n</blockquote>\n<script async src=\"https://platform.twitter.com/widgets.js\" charset=\"utf-8\"></script>\n", "liked_at": "2025-08-25T15:21:12.207016", "source": "ifttt"}