{"tweet_id": "1971476729614172544", "text": "oh my.. this GeoSpy AI can track your exact location using social media photos https://t.co/9Wz9YO5dKx", "username": "EHuanglu", "tweet_url": "https://twitter.com/EHuanglu/status/1971476729614172544", "first_link": "https://x.com/EHuanglu/status/1971476729614172544/video/1", "created_at": "September 26, 2025 at 07:27AM", "embed_code": "<blockquote class=\"twitter-tweet\">\n  <p lang=\"en\" dir=\"ltr\">oh my.. this GeoSpy AI can track your exact location using social media photos https://t.co/9Wz9YO5dKx</p>\n  &mdash; el.cine (@EHuanglu)\n  <a href=\"https://twitter.com/EHuanglu/status/1971476729614172544\">Sep 26, 2025</a>\n</blockquote>\n<script async src=\"https://platform.twitter.com/widgets.js\" charset=\"utf-8\"></script>\n", "liked_at": "2025-09-26T16:46:45.478891", "source": "ifttt"}