{"tweet_id": "2006269681389429121", "text": "今年もダッシュでやってきた年越しそば https://t.co/ZbFMmV4UPQ", "username": "hattori2000", "tweet_url": "https://twitter.com/hattori2000/status/2006269681389429121", "first_link": "https://x.com/hattori2000/status/2006269681389429121/photo/1", "created_at": "December 31, 2025 at 07:42AM", "embed_code": "<blockquote class=\"twitter-tweet\">\n  <p lang=\"en\" dir=\"ltr\">今年もダッシュでやってきた年越しそば https://t.co/ZbFMmV4UPQ</p>\n  &mdash; 服部グラフィクス (@hattori2000)\n  <a href=\"https://twitter.com/hattori2000/status/2006269681389429121\">Dec 31, 2025</a>\n</blockquote>\n<script async src=\"https://platform.twitter.com/widgets.js\" charset=\"utf-8\"></script>\n", "liked_at": "2025-12-31T13:31:26.956140", "source": "ifttt"}