{"tweet_id": "2055202885022175363", "text": "7月去日本？避開 35 度的 3 個山岳避暑地｜+1000 米的魔法｜日本一分鐘 022 https://t.co/Sk0uQL4moe @YouTubeより", "username": "ribenyifenzhong", "tweet_url": "https://twitter.com/ribenyifenzhong/status/2055202885022175363", "first_link": "https://youtube.com/shorts/mxupf2HqVhI?si=UPB3kONkjJkTG8Z_", "created_at": "May 15, 2026 at 05:25PM", "embed_code": "<blockquote class=\"twitter-tweet\">\n  <p lang=\"en\" dir=\"ltr\">7月去日本？避開 35 度的 3 個山岳避暑地｜+1000 米的魔法｜日本一分鐘 022 https://t.co/Sk0uQL4moe @YouTubeより</p>\n  &mdash; 日本一分鐘 (@ribenyifenzhong)\n  <a href=\"https://twitter.com/ribenyifenzhong/status/2055202885022175363\">May 15, 2026</a>\n</blockquote>\n<script async src=\"https://platform.twitter.com/widgets.js\" charset=\"utf-8\"></script>\n", "liked_at": "2026-05-15T14:41:40.643681", "source": "ifttt"}