{"tweet_id": "2064890533869461813", "text": "ポン出しだと情報量がうるさい、を伝える例 https://t.co/ENj6BDB91N", "username": "_watany", "tweet_url": "https://twitter.com/_watany/status/2064890533869461813", "first_link": "https://x.com/_watany/status/2064890533869461813/photo/1", "created_at": "June 11, 2026 at 11:00AM", "embed_code": "<blockquote class=\"twitter-tweet\">\n  <p lang=\"en\" dir=\"ltr\">ポン出しだと情報量がうるさい、を伝える例 https://t.co/ENj6BDB91N</p>\n  &mdash; watany (@_watany)\n  <a href=\"https://twitter.com/_watany/status/2064890533869461813\">Jun 11, 2026</a>\n</blockquote>\n<script async src=\"https://platform.twitter.com/widgets.js\" charset=\"utf-8\"></script>\n", "liked_at": "2026-06-12T07:31:26.774789", "source": "ifttt"}