{"text": "ブラウザで動く無料作曲ソフト、アップデートで良い感じになってるのでみんな遊んでみてね。\n・MIDI読み込み保存\n・mp3書き出し\n・SoundFont対応\n・MIDIキーボード対応\nhttps://t.co/Ffful639ar https://t.co/twvmCuOkCd", "username": "ryoheyc", "tweet_url": "https://twitter.com/ryoheyc/status/1889260247375880219", "first_link": "https://signal.vercel.app/", "created_at": "February 11, 2025 at 10:28AM", "embed_code": "<blockquote class=\"twitter-tweet\">\n  <p lang=\"en\" dir=\"ltr\">ブラウザで動く無料作曲ソフト、アップデートで良い感じになってるのでみんな遊んでみてね。\n・MIDI読み込み保存\n・mp3書き出し\n・SoundFont対応\n・MIDIキーボード対応\nhttps://t.co/Ffful639ar https://t.co/twvmCuOkCd</p>\n  &mdash; ryohey (@ryoheyc)\n  <a href=\"https://twitter.com/ryoheyc/status/1889260247375880219\">Feb 11, 2025</a>\n</blockquote>\n<script async src=\"https://platform.twitter.com/widgets.js\" charset=\"utf-8\"></script>\n", "liked_at": "2025-02-11T15:21:40.823288", "source": "ifttt"}